<manifest alg="2" build="2018.0.0.379" opt="false" iceEnabled="true" iceMarkupVersion="2" iceEnabledOptions="link,responsive,cachebuster,textStyling" exportTarget="other" domain="skyeng.ru" resolutions="1x" timestamp="1517257951098">
  <folder name="css">
    <file name="site_global.css" crc="384377044"/>
    <file name="index.css" crc="4225865557" ref="index"/>
    <file name="nomq_index.css" crc="349363884" ref="index"/>
  </folder>
  <folder name="fonts">
    <file name="museosanscyrl-500.woff" crc="427418235"/>
    <file name="museosanscyrl-500.eot" crc="4098049931"/>
    <file name="museosanscyrl-500.svg" crc="440066275"/>
    <file name="museosanscyrl-300.woff" crc="3942259165"/>
    <file name="museosanscyrl-300.eot" crc="3834028192"/>
    <file name="museosanscyrl-300.svg" crc="508922106"/>
    <file name="montserrat-bold.woff" crc="4119092551"/>
    <file name="montserrat-bold.eot" crc="186350765"/>
    <file name="montserrat-bold.svg" crc="465511547"/>
    <file name="museosanscyrl-900.woff" crc="205297370"/>
    <file name="museosanscyrl-900.eot" crc="459841282"/>
    <file name="museosanscyrl-900.svg" crc="421324779"/>
  </folder>
  <folder name="assets">
    <file name="youtube.jpg" crc="93917794" seo="true" mt="1510087115000"/>
  </folder>
  <folder name="scripts">
    <file name="jquery-1.8.3.min.js" crc="209076791" ref="index"/>
    <file name="museutils.js" crc="3803043152" ref="index"/>
    <file name="whatinput.js" crc="86476730" ref="index"/>
    <file name="museconfig.js" crc="380897831" ref="index"/>
    <file name="jquery.musepolyfill.bgsize.js" crc="4148998990" ref="index"/>
    <file name="jquery.watch.js" crc="99325471" ref="index"/>
    <file name="webpro.js" crc="242022427" ref="index"/>
    <file name="form_check.php" crc="147359589" ref="index"/>
    <file name="form_throttle.php" crc="93986428" ref="index"/>
    <file name="form_process.php" crc="3851993751" ref="index"/>
    <file name="form-u1157.php" crc="3774522568" ref="index"/>
    <file name="form-u12767.php" crc="80901942" ref="index"/>
    <file name="jquery.musemenu.js" crc="3784699396" ref="index"/>
    <file name="musewpdisclosure.js" crc="119288625" ref="index"/>
    <file name="html5shiv.js" crc="4241844378" ref="index"/>
    <file name="jquery.museresponsive.js" crc="3955820958" ref="index"/>
    <file name="require.js" crc="4157109226" ref="index"/>
  </folder>
  <folder name="images">
    <file name="bg.jpg" crc="296959571" ref="index">
      <caption webpage="index" alt=""/>
    </file>
    <file name="united-kingdom.svg" crc="3782371471" ref="index"/>
    <file name="united-kingdom_poster_u129.png" crc="4278749667" ref="index"/>
    <file name="logo-white.svg" crc="399739604" ref="index"/>
    <file name="logo-white_poster_u262.png" crc="3759937272" ref="index"/>
    <file name="technology-(1).svg" crc="3914804533" seo="true" ref="index">
      <caption webpage="index" alt=""/>
    </file>
    <file name="technology (1)_poster_.png" crc="4138306781" ref="index"/>
    <file name="line_white-03.svg" crc="451982212" ref="index"/>
    <file name="line_white-03_poster_u224.png" crc="4258776521" ref="index"/>
    <file name="bg_woman.jpg" crc="3788888132" ref="index">
      <caption webpage="index" alt=""/>
      <caption webpage="index" alt=""/>
      <caption webpage="index" alt=""/>
    </file>
    <file name="nikolaeva.png" crc="140890134" ref="index">
      <caption webpage="index" alt=""/>
    </file>
    <file name="arrow-02.svg" crc="4141814564" ref="index"/>
    <file name="arrow-02_poster_u11904.png" crc="121045358" ref="index"/>
    <file name="arrow-04.svg" crc="4158795398" ref="index"/>
    <file name="arrow-04_poster_u11920.png" crc="239548594" ref="index"/>
    <file name="circles-06.svg" crc="426381891" seo="true" ref="index">
      <caption webpage="index" alt=""/>
      <caption webpage="index" alt=""/>
      <caption webpage="index" alt=""/>
    </file>
    <file name="circles-06_poster_.png" crc="201668373" ref="index"/>
    <file name="bg_deal-u4997-fr.jpg" crc="251941954" ref="index"/>
    <file name="005-united-kingdom.svg" crc="94862995" ref="index"/>
    <file name="005-united-kingdom_poster_u5043.png" crc="4083150413" ref="index"/>
    <file name="004-ethernet.svg" crc="253236894" ref="index"/>
    <file name="004-ethernet_poster_u5054.png" crc="177032394" ref="index"/>
    <file name="003-professor.svg" crc="195980999" ref="index"/>
    <file name="003-professor_poster_u5065.png" crc="503328112" ref="index"/>
    <file name="002-people.svg" crc="321471626" ref="index"/>
    <file name="002-people_poster_u5084.png" crc="485707899" ref="index"/>
    <file name="001-profits.svg" crc="210176970" ref="index"/>
    <file name="001-profits_poster_u5095.png" crc="360951500" ref="index"/>
    <file name="bg_register-u5455-fr.jpg" crc="379342470" ref="index"/>
    <file name="hand_ruble-02-02.svg" crc="4005462149" seo="true" ref="index">
      <caption webpage="index" alt=""/>
      <caption webpage="index" alt=""/>
      <caption webpage="index" alt=""/>
    </file>
    <file name="hand_ruble-02-02_poster_.png" crc="4045707913" ref="index"/>
    <file name="menu.svg" crc="386557886" ref="index"/>
    <file name="menu_poster_u13855.png" crc="3958630153" ref="index"/>
    <file name="bg_deal.jpg" crc="3768873821" ref="index">
      <caption webpage="index" alt=""/>
    </file>
    <file name="bg_register.jpg" crc="4161686074" ref="index">
      <caption webpage="index" alt=""/>
    </file>
    <file name="blank.gif" crc="4208392903" ref="index"/>
  </folder>
  <file name="index.html" crc="3992253889" seo="true" mt="1517257909447" redirect="true"/>
</manifest>